MANIFEST.in
VERSION
setup.cfg
setup.py
tests/__init__.py
tests/test_trh.py
tornado_rest_handler/__init__.py
tornado_rest_handler/trh.py
tornado_rest_handler.egg-info/PKG-INFO
tornado_rest_handler.egg-info/SOURCES.txt
tornado_rest_handler.egg-info/dependency_links.txt
tornado_rest_handler.egg-info/requires.txt
tornado_rest_handler.egg-info/top_level.txt