Metadata-Version: 1.1
Name: tornado-rest-handler
Version: 0.0.7
Summary: A simple Python Tornado handler that manage Rest requests automatically.
Home-page: https://github.com/paulocheque/tornado-rest-handler
Author: paulocheque
Author-email: paulocheque@gmail.com
License: MIT
Keywords: python tornado rest handler
Platform: UNKNOWN
Classifier: Operating System :: OS Independent
Classifier: Topic :: Software Development
